gram/__init__.py
gram/gram.py
py_grimm-0.0.7.dist-info/LICENSE
py_grimm-0.0.7.dist-info/METADATA
py_grimm-0.0.7.dist-info/WHEEL
py_grimm-0.0.7.dist-info/top_level.txt
py_grimm-0.0.7.dist-info/RECORD
