Metadata-Version: 2.1
Name: py-grimm
Version: 0.0.7
Summary: Python Boilerplate contains all the boilerplate you need to create a Python package.
Home-page: https://github.com/nmdp-bioinformatics/gram
Author: Pradeep Bashyal
Author-email: pbashyal@nmdp.org
License: LGPL 3.0
Keywords: graph,em,family
Platform: UNKNOWN
Classifier: Development Status :: 2 - Pre-Alpha
Classifier: Intended Audience :: Developers
Classifier: License :: OSI Approved :: GNU Lesser General Public License v3 (LGPLv3)
Classifier: Natural Language :: English
Classifier: Programming Language :: Python :: 3.8
Classifier: Programming Language :: Python :: 3.9
Classifier: Programming Language :: Python :: 3.10
Requires-Python: >=3.8
License-File: LICENSE
Requires-Dist: toml (==0.10.2)
Requires-Dist: py-graph-imputation (>=0.0.3)
